{
    "$jason": {
        "head": {
            "title" : "Simple shit right now"
        },
        "body": {
            "header": {
                "title": "MLP Mexico",
                "menu": {
                    "text": "Home",
                    "href": {
                        "url": "file://hello.json"
                    }
                }
            },
            "sections": [{
                "items": [
                    {"type": "vertical",
                        "style": {"spacing": "5"},
                        "components": [
                            {"type": "button", "url": "file://VideoModules.png", "href": {"url": "file://videos.json"}},
                            {"type": "button", "url": "file://DownloadableMaterials.png", "href": {"url": "file://stub.json"}},
                            {"type": "button", "url": "file://Feedback.png", "href": {"url": "file://stub.json"}},
                            {"type": "button", "url": "file://FacebookPage.png", "href": {"url": "file://stub.json"}},
                            {"type": "button", "url": "file://Instagram.png", "href": {"url": "file://stub.json"}}
                        ]
                    }
                ]
            }]
        }
    }
}
